AUTHORS.rst
LICENSE.rst
README.rst
ez_setup.py
setup.py
getprox/__init__.py
getprox/getters.py
getprox/pg.py
getprox/proxytest.py
getprox/version.py
getprox.egg-info/PKG-INFO
getprox.egg-info/SOURCES.txt
getprox.egg-info/dependency_links.txt
getprox.egg-info/pbr.json
getprox.egg-info/requires.txt
getprox.egg-info/top_level.txt