Metadata-Version: 1.1
Name: getprox
Version: 0.1.1
Summary: Retrieve lists of free HTTP proxies from online sites.
Home-page: https://github.com/lebedov/getprox
Author: Lev Givon
Author-email: lev@columbia.edu
License: BSD
Platform: UNKNOWN
Classifier: Development Status :: 3 - Alpha
Classifier: Intended Audience :: Developers
Classifier: License :: OSI Approved :: BSD License
Classifier: Operating System :: OS Independent
Classifier: Programming Language :: Python
Classifier: Topic :: Software Development
